Metadata-Version: 2.1
Name: botbuilder-sangamam-cognitive-text-translate
Version: 0.1.0
Summary: Microsoft Bot Builder sangamam Middleware test recognizer
Home-page: https://github.com/rvinothrajendran
Author: Bot Builder sangamam
Author-email: r.vinoth@live.com
License: MIT
Keywords: botbuilder bots ai botframework middleware text translate
Platform: UNKNOWN
Classifier: Programming Language :: Python :: 3.8
Classifier: Intended Audience :: Developers
Classifier: License :: OSI Approved :: MIT License
Classifier: Operating System :: OS Independent
Classifier: Development Status :: 3 - Alpha
Classifier: Topic :: Scientific/Engineering :: Artificial Intelligence
